airsspy/__init__.py
airsspy/build.py
airsspy/common.py
airsspy/restools.py
airsspy/seed.py
airsspy/tests/__init__.py
airsspy/tests/conftest.py
airsspy/tests/test_build.py
airsspy/tests/test_restools.py
airsspy/tests/test_seed.py
airsspy-0.1.3.dist-info/LICENSE
airsspy-0.1.3.dist-info/METADATA
airsspy-0.1.3.dist-info/WHEEL
airsspy-0.1.3.dist-info/top_level.txt
airsspy-0.1.3.dist-info/RECORD
