Metadata-Version: 2.1
Name: airsspy
Version: 0.1.3
Summary: A wrapper for using AIRSS with python and ase.
Home-page: https://github.com/zhubonan/airsspy
Maintainer: Bonan Zhu
Maintainer-email: bon.zhu@protonmail.com
License: UNKNOWN
Platform: UNKNOWN
Requires-Dist: ase (~=3.17)
Requires-Dist: castepinput (~=0.1)
Provides-Extra: pre-commit
Requires-Dist: pre-commit (==1.11.0) ; extra == 'pre-commit'
Requires-Dist: yapf (==0.24.0) ; extra == 'pre-commit'
Provides-Extra: testing
Requires-Dist: pytest ; extra == 'testing'
